{
  "oferte": [
    {
      "categorie": "ruseasca",
      "data-incepere": "2025-06-17T10:12:36.627Z",
      "data-finalizare": "2025-06-17T10:14:36.627Z",
      "reducere": 30
    },
    {
      "categorie": "franceza",
      "data-incepere": "2025-06-17T10:10:36.582Z",
      "data-finalizare": "2025-06-17T10:12:36.582Z",
      "reducere": 40
    },
    {
      "categorie": "italiana",
      "data-incepere": "2025-06-17T10:08:23.257Z",
      "data-finalizare": "2025-06-17T10:10:23.257Z",
      "reducere": 30
    },
    {
      "categorie": "franceza",
      "data-incepere": "2025-06-17T10:06:23.224Z",
      "data-finalizare": "2025-06-17T10:08:23.224Z",
      "reducere": 35
    },
    {
      "categorie": "romaneasca",
      "data-incepere": "2025-06-17T10:04:23.193Z",
      "data-finalizare": "2025-06-17T10:06:23.193Z",
      "reducere": 20
    },
    {
      "categorie": "franceza",
      "data-incepere": "2025-06-17T10:02:23.156Z",
      "data-finalizare": "2025-06-17T10:04:23.156Z",
      "reducere": 25
    },
    {
      "categorie": "italiana",
      "data-incepere": "2025-06-17T10:00:21.143Z",
      "data-finalizare": "2025-06-17T10:02:21.143Z",
      "reducere": 20
    },
    {
      "categorie": "franceza",
      "data-incepere": "2025-06-17T09:58:21.100Z",
      "data-finalizare": "2025-06-17T10:00:21.100Z",
      "reducere": 20
    },
    {
      "categorie": "romaneasca",
      "data-incepere": "2025-06-17T09:56:21.059Z",
      "data-finalizare": "2025-06-17T09:58:21.059Z",
      "reducere": 20
    }
  ]
}